anthill/__init__.py
anthill/anthill.py
anthill/cli.py
anthill/main/__init__.py
anthill/main/cli/__init__.py
anthill/main/cli/core.py
anthill/src/__init__.py
anthill/src/__main__.py
anthill/src/cli/__init__.py
anthill/src/cli/core.py
anthill/src/cli/management.py
anthill/src/topology/__init__.py
anthill/src/topology/constants.py
anthill/src/topology/topology.py
anthill/src/topology/transform.py
anthill-1.0.3.dist-info/AUTHORS.rst
anthill-1.0.3.dist-info/LICENSE
anthill-1.0.3.dist-info/METADATA
anthill-1.0.3.dist-info/WHEEL
anthill-1.0.3.dist-info/entry_points.txt
anthill-1.0.3.dist-info/top_level.txt
anthill-1.0.3.dist-info/RECORD
