Metadata-Version: 2.1
Name: anthill
Version: 1.0.3
Summary: An intelligent general purpose automation system.
Home-page: https://github.com/ayushpallav/anthill
Author: Ayush Pallav
Author-email: ayushpallav@gmail.com
License: MIT license
Keywords: anthill
Platform: UNKNOWN
Classifier: Development Status :: 2 - Pre-Alpha
Classifier: Intended Audience :: Developers
Classifier: License :: OSI Approved :: MIT License
Classifier: Natural Language :: English
Classifier: Programming Language :: Python :: 3
Classifier: Programming Language :: Python :: 3.5
Classifier: Programming Language :: Python :: 3.6
Classifier: Programming Language :: Python :: 3.7
Classifier: Programming Language :: Python :: 3.8
Requires-Python: >=3.5
Requires-Dist: Click (>=7.0)
Requires-Dist: PyYAML (==5.3.1)
Requires-Dist: jsonschema (==3.2.0)
